{
  "ok": true,
  "animations": {
    "waiting": {
      "ok": true,
      "frame_count": 12,
      "frame_duration_ms": 210,
      "loop": true,
      "dimensions": [
        1152,
        1248
      ],
      "hidden_rgb_pixels_under_zero_alpha": 0,
      "touches_safety_edge": false,
      "maximum_center_drift_px": 0.0,
      "maximum_baseline_drift_px": 0,
      "unique_frame_hashes": 12,
      "alpha_bboxes": [
        [
          142,
          44,
          952,
          1214
        ],
        [
          142,
          44,
          952,
          1214
        ],
        [
          142,
          44,
          952,
          1214
        ],
        [
          142,
          44,
          952,
          1214
        ],
        [
          142,
          44,
          952,
          1214
        ],
        [
          142,
          44,
          952,
          1214
        ],
        [
          142,
          44,
          952,
          1214
        ],
        [
          142,
          44,
          952,
          1214
        ],
        [
          142,
          44,
          952,
          1214
        ],
        [
          142,
          44,
          952,
          1214
        ],
        [
          142,
          44,
          952,
          1214
        ],
        [
          142,
          44,
          952,
          1214
        ]
      ],
      "artifacts": {
        "contact_sheet": "waiting-contact-sheet.png",
        "preview": "waiting-preview.gif"
      }
    },
    "working": {
      "ok": true,
      "frame_count": 16,
      "frame_duration_ms": 145,
      "loop": true,
      "dimensions": [
        1152,
        1248
      ],
      "hidden_rgb_pixels_under_zero_alpha": 0,
      "touches_safety_edge": false,
      "maximum_center_drift_px": 0.0,
      "maximum_baseline_drift_px": 0,
      "unique_frame_hashes": 16,
      "alpha_bboxes": [
        [
          135,
          60,
          925,
          1214
        ],
        [
          135,
          60,
          925,
          1214
        ],
        [
          135,
          60,
          925,
          1214
        ],
        [
          135,
          60,
          925,
          1214
        ],
        [
          135,
          60,
          925,
          1214
        ],
        [
          135,
          60,
          925,
          1214
        ],
        [
          135,
          60,
          925,
          1214
        ],
        [
          135,
          60,
          925,
          1214
        ],
        [
          135,
          60,
          925,
          1214
        ],
        [
          135,
          60,
          925,
          1214
        ],
        [
          135,
          60,
          925,
          1214
        ],
        [
          135,
          60,
          925,
          1214
        ],
        [
          135,
          60,
          925,
          1214
        ],
        [
          135,
          60,
          925,
          1214
        ],
        [
          135,
          60,
          925,
          1214
        ],
        [
          135,
          60,
          925,
          1214
        ]
      ],
      "artifacts": {
        "contact_sheet": "working-contact-sheet.png",
        "preview": "working-preview.gif"
      }
    },
    "review": {
      "ok": true,
      "frame_count": 12,
      "frame_duration_ms": 210,
      "loop": true,
      "dimensions": [
        1152,
        1248
      ],
      "hidden_rgb_pixels_under_zero_alpha": 0,
      "touches_safety_edge": false,
      "maximum_center_drift_px": 0.0,
      "maximum_baseline_drift_px": 0,
      "unique_frame_hashes": 11,
      "alpha_bboxes": [
        [
          135,
          64,
          925,
          1214
        ],
        [
          135,
          64,
          925,
          1214
        ],
        [
          135,
          64,
          925,
          1214
        ],
        [
          135,
          64,
          925,
          1214
        ],
        [
          135,
          64,
          925,
          1214
        ],
        [
          135,
          64,
          925,
          1214
        ],
        [
          135,
          64,
          925,
          1214
        ],
        [
          135,
          64,
          925,
          1214
        ],
        [
          135,
          64,
          925,
          1214
        ],
        [
          135,
          64,
          925,
          1214
        ],
        [
          135,
          64,
          925,
          1214
        ],
        [
          135,
          64,
          925,
          1214
        ]
      ],
      "artifacts": {
        "contact_sheet": "review-contact-sheet.png",
        "preview": "review-preview.gif"
      }
    },
    "failure": {
      "ok": true,
      "frame_count": 14,
      "frame_duration_ms": 140,
      "loop": false,
      "dimensions": [
        1152,
        1248
      ],
      "hidden_rgb_pixels_under_zero_alpha": 0,
      "touches_safety_edge": false,
      "maximum_center_drift_px": 157.5,
      "maximum_baseline_drift_px": 0,
      "unique_frame_hashes": 14,
      "alpha_bboxes": [
        [
          142,
          48,
          952,
          1214
        ],
        [
          142,
          56,
          952,
          1214
        ],
        [
          142,
          73,
          952,
          1214
        ],
        [
          142,
          90,
          952,
          1214
        ],
        [
          142,
          140,
          952,
          1214
        ],
        [
          142,
          221,
          952,
          1214
        ],
        [
          142,
          320,
          952,
          1214
        ],
        [
          142,
          363,
          952,
          1214
        ],
        [
          142,
          363,
          952,
          1214
        ],
        [
          142,
          363,
          952,
          1214
        ],
        [
          142,
          363,
          952,
          1214
        ],
        [
          142,
          363,
          952,
          1214
        ],
        [
          142,
          363,
          952,
          1214
        ],
        [
          142,
          363,
          952,
          1214
        ]
      ],
      "artifacts": {
        "contact_sheet": "failure-contact-sheet.png",
        "preview": "failure-preview.gif"
      }
    }
  }
}
